{
"meta":{"test_sets":[],"test_metrics":[],"learn_metrics":[{"best_value":"Min","name":"RMSE"}],"launch_mode":"Train","parameters":"","iteration_count":500,"learn_sets":["learn"],"name":"experiment"},
"iterations":[
{"learn":[559.8989619],"iteration":0,"passed_time":0.002425938588,"remaining_time":1.210543355},
{"learn":[558.1315142],"iteration":1,"passed_time":0.003730902392,"remaining_time":0.9289946957},
{"learn":[556.4997597],"iteration":2,"passed_time":0.004777589941,"remaining_time":0.7914874002},
{"learn":[554.9270639],"iteration":3,"passed_time":0.005941520494,"remaining_time":0.7367485413},
{"learn":[553.3633793],"iteration":4,"passed_time":0.007762453513,"remaining_time":0.7684828978},
{"learn":[552.044393],"iteration":5,"passed_time":0.009117789312,"remaining_time":0.7506979867},
{"learn":[550.8193988],"iteration":6,"passed_time":0.01035975688,"remaining_time":0.7296228771},
{"learn":[549.5296225],"iteration":7,"passed_time":0.01155468558,"remaining_time":0.7106131631},
{"learn":[548.0882596],"iteration":8,"passed_time":0.01292047909,"remaining_time":0.7048839147},
{"learn":[546.950014],"iteration":9,"passed_time":0.01405832786,"remaining_time":0.6888580654},
{"learn":[545.9001684],"iteration":10,"passed_time":0.01533845982,"remaining_time":0.6818642592},
{"learn":[544.882129],"iteration":11,"passed_time":0.01661050892,"remaining_time":0.6754940294},
{"learn":[543.5559487],"iteration":12,"passed_time":0.01796980282,"remaining_time":0.6731764593},
{"learn":[542.7917515],"iteration":13,"passed_time":0.01903736412,"remaining_time":0.6608684973},
{"learn":[541.8739094],"iteration":14,"passed_time":0.02012375763,"remaining_time":0.6506681634},
{"learn":[541.0128463],"iteration":15,"passed_time":0.0212170674,"remaining_time":0.6418162888},
{"learn":[540.0197221],"iteration":16,"passed_time":0.02230100272,"remaining_time":0.6336108421},
{"learn":[539.1481904],"iteration":17,"passed_time":0.0234126864,"remaining_time":0.6269397135},
{"learn":[538.363682],"iteration":18,"passed_time":0.02449924656,"remaining_time":0.6202177683},
{"learn":[537.5043824],"iteration":19,"passed_time":0.02566021896,"remaining_time":0.6158452551},
{"learn":[536.9011547],"iteration":20,"passed_time":0.02668578277,"remaining_time":0.6086899975},
{"learn":[536.2992534],"iteration":21,"passed_time":0.02776630163,"remaining_time":0.6032860082},
{"learn":[535.591321],"iteration":22,"passed_time":0.02881903049,"remaining_time":0.5976816323},
{"learn":[534.9442506],"iteration":23,"passed_time":0.02986051001,"remaining_time":0.5922334486},
{"learn":[534.2770442],"iteration":24,"passed_time":0.0310216074,"remaining_time":0.5894105406},
{"learn":[533.7304008],"iteration":25,"passed_time":0.03212970795,"remaining_time":0.5857492911},
{"learn":[532.967954],"iteration":26,"passed_time":0.03330555446,"remaining_time":0.5834639726},
{"learn":[532.1791452],"iteration":27,"passed_time":0.03431378597,"remaining_time":0.5784323921},
{"learn":[531.5438763],"iteration":28,"passed_time":0.03546196746,"remaining_time":0.5759512647},
{"learn":[530.9664824],"iteration":29,"passed_time":0.03638837052,"remaining_time":0.5700844715},
{"learn":[530.3779748],"iteration":30,"passed_time":0.0373921023,"remaining_time":0.5657063219},
{"learn":[529.7515323],"iteration":31,"passed_time":0.03851570193,"remaining_time":0.5632921407},
{"learn":[529.1577704],"iteration":32,"passed_time":0.03961571963,"remaining_time":0.5606224565},
{"learn":[528.5422348],"iteration":33,"passed_time":0.04064124177,"remaining_time":0.5570240784},
{"learn":[528.1395806],"iteration":34,"passed_time":0.04173542649,"remaining_time":0.5544849519},
{"learn":[527.6461146],"iteration":35,"passed_time":0.04287181702,"remaining_time":0.552570086},
{"learn":[527.2722095],"iteration":36,"passed_time":0.04393208709,"remaining_time":0.5497447654},
{"learn":[526.841307],"iteration":37,"passed_time":0.04496285892,"remaining_time":0.5466537058},
{"learn":[526.2889297],"iteration":38,"passed_time":0.04614337182,"remaining_time":0.5454383181},
{"learn":[525.8887479],"iteration":39,"passed_time":0.04820787364,"remaining_time":0.5543905468},
{"learn":[525.3970035],"iteration":40,"passed_time":0.04951804546,"remaining_time":0.5543605577},
{"learn":[524.9922598],"iteration":41,"passed_time":0.05062193793,"remaining_time":0.5520201803},
{"learn":[524.6071035],"iteration":42,"passed_time":0.05166108426,"remaining_time":0.5490491979},
{"learn":[524.1572953],"iteration":43,"passed_time":0.05261919376,"remaining_time":0.5453261899},
{"learn":[523.7498512],"iteration":44,"passed_time":0.05367188095,"remaining_time":0.5426823519},
{"learn":[523.3860788],"iteration":45,"passed_time":0.0548062716,"remaining_time":0.5409140719},
{"learn":[523.1157547],"iteration":46,"passed_time":0.0558180029,"remaining_time":0.5379905386},
{"learn":[522.8382888],"iteration":47,"passed_time":0.05689252212,"remaining_time":0.5357379167},
{"learn":[522.5147874],"iteration":48,"passed_time":0.05787692172,"remaining_time":0.5327039122},
{"learn":[522.1074243],"iteration":49,"passed_time":0.05891052672,"remaining_time":0.5301947405},
{"learn":[521.8122602],"iteration":50,"passed_time":0.06001341925,"remaining_time":0.5283534361},
{"learn":[521.4904043],"iteration":51,"passed_time":0.06101127638,"remaining_time":0.5256356119},
{"learn":[521.0800892],"iteration":52,"passed_time":0.06205058936,"remaining_time":0.5233323292},
{"learn":[520.605963],"iteration":53,"passed_time":0.06365203548,"remaining_time":0.5257186634},
{"learn":[520.2080674],"iteration":54,"passed_time":0.06471768023,"remaining_time":0.5236248673},
{"learn":[519.8316321],"iteration":55,"passed_time":0.06566179057,"remaining_time":0.5206041966},
{"learn":[519.5071113],"iteration":56,"passed_time":0.06665885607,"remaining_time":0.5180679516},
{"learn":[519.1286879],"iteration":57,"passed_time":0.06762229859,"remaining_time":0.5153285513},
{"learn":[518.7157633],"iteration":58,"passed_time":0.06868477686,"remaining_time":0.5133896033},
{"learn":[518.4208383],"iteration":59,"passed_time":0.06969729978,"remaining_time":0.5111135317},
{"learn":[518.1458003],"iteration":60,"passed_time":0.07070898942,"remaining_time":0.5088728911},
{"learn":[517.8727634],"iteration":61,"passed_time":0.0717299285,"remaining_time":0.5067372369},
{"learn":[517.5116271],"iteration":62,"passed_time":0.07285548635,"remaining_time":0.5053626593},
{"learn":[517.254851],"iteration":63,"passed_time":0.07375472436,"remaining_time":0.5024540597},
{"learn":[517.016363],"iteration":64,"passed_time":0.07469246008,"remaining_time":0.4998649251},
{"learn":[516.7223939],"iteration":65,"passed_time":0.07563173737,"remaining_time":0.49733597},
{"learn":[516.5612511],"iteration":66,"passed_time":0.07680191755,"remaining_time":0.4963467209},
{"learn":[516.3749046],"iteration":67,"passed_time":0.07779889973,"remaining_time":0.4942518336},
{"learn":[516.1578218],"iteration":68,"passed_time":0.07879259044,"remaining_time":0.4921682098},
{"learn":[515.9573044],"iteration":69,"passed_time":0.07984452767,"remaining_time":0.4904735271},
{"learn":[515.7574672],"iteration":70,"passed_time":0.08088163246,"remaining_time":0.4887073285},
{"learn":[515.5770975],"iteration":71,"passed_time":0.08198110853,"remaining_time":0.4873321451},
{"learn":[515.350948],"iteration":72,"passed_time":0.08305675268,"remaining_time":0.485825115},
{"learn":[515.1530311],"iteration":73,"passed_time":0.08409514906,"remaining_time":0.4841153175},
{"learn":[515.0115684],"iteration":74,"passed_time":0.0851178797,"remaining_time":0.4823346516},
{"learn":[514.7400374],"iteration":75,"passed_time":0.08611761172,"remaining_time":0.4804456233},
{"learn":[514.5104747],"iteration":76,"passed_time":0.08714630034,"remaining_time":0.4787387668},
{"learn":[514.3651931],"iteration":77,"passed_time":0.08820011246,"remaining_time":0.4771852238},
{"learn":[514.0509538],"iteration":78,"passed_time":0.08942149792,"remaining_time":0.4765373497},
{"learn":[513.6793671],"iteration":79,"passed_time":0.09066029901,"remaining_time":0.4759665698},
{"learn":[513.5047017],"iteration":80,"passed_time":0.09175298381,"remaining_time":0.4746234595},
{"learn":[513.3040625],"iteration":81,"passed_time":0.09276688165,"remaining_time":0.4728848357},
{"learn":[513.0709413],"iteration":82,"passed_time":0.09376544707,"remaining_time":0.4710866437},
{"learn":[512.8565567],"iteration":83,"passed_time":0.09490650399,"remaining_time":0.4700131626},
{"learn":[512.6894456],"iteration":84,"passed_time":0.09585940547,"remaining_time":0.4680194502},
{"learn":[512.4341189],"iteration":85,"passed_time":0.09684880477,"remaining_time":0.4662256415},
{"learn":[512.2402263],"iteration":86,"passed_time":0.09783145447,"remaining_time":0.4644182839},
{"learn":[512.0849344],"iteration":87,"passed_time":0.09887451723,"remaining_time":0.4629125125},
{"learn":[511.9152431],"iteration":88,"passed_time":0.09995220293,"remaining_time":0.461577027},
{"learn":[511.7623476],"iteration":89,"passed_time":0.1009940991,"remaining_time":0.4600842292},
{"learn":[511.5981963],"iteration":90,"passed_time":0.1020513693,"remaining_time":0.4586704403},
{"learn":[511.4298672],"iteration":91,"passed_time":0.1031430959,"remaining_time":0.4574172078},
{"learn":[511.2503496],"iteration":92,"passed_time":0.1040905393,"remaining_time":0.4555360163},
{"learn":[511.0673154],"iteration":93,"passed_time":0.1051377685,"remaining_time":0.4541056811},
{"learn":[511.0166248],"iteration":94,"passed_time":0.1063549876,"remaining_time":0.4534081049},
{"learn":[510.8548721],"iteration":95,"passed_time":0.1080435952,"remaining_time":0.4546834629},
{"learn":[510.6836529],"iteration":96,"passed_time":0.1094316373,"remaining_time":0.4546489675},
{"learn":[510.5413457],"iteration":97,"passed_time":0.1103903718,"remaining_time":0.4528258108},
{"learn":[510.3598822],"iteration":98,"passed_time":0.1113623971,"remaining_time":0.451073952},
{"learn":[510.2150776],"iteration":99,"passed_time":0.1123462968,"remaining_time":0.449385187},
{"learn":[510.0391733],"iteration":100,"passed_time":0.1133985256,"remaining_time":0.4479803142},
{"learn":[509.888096],"iteration":101,"passed_time":0.1144283392,"remaining_time":0.4464948922},
{"learn":[509.6994782],"iteration":102,"passed_time":0.1154299461,"remaining_time":0.4449095981},
{"learn":[509.564546],"iteration":103,"passed_time":0.1165307971,"remaining_time":0.4437134197},
{"learn":[509.4302056],"iteration":104,"passed_time":0.1175494863,"remaining_time":0.4422099723},
{"learn":[509.2719394],"iteration":105,"passed_time":0.1185633008,"remaining_time":0.4406975521},
{"learn":[509.1116174],"iteration":106,"passed_time":0.1196792342,"remaining_time":0.4395695239},
{"learn":[508.9151286],"iteration":107,"passed_time":0.1211238147,"remaining_time":0.4396345867},
{"learn":[508.8239253],"iteration":108,"passed_time":0.1226396826,"remaining_time":0.4399276688},
{"learn":[508.7052988],"iteration":109,"passed_time":0.1238469439,"remaining_time":0.4390937102},
{"learn":[508.4916816],"iteration":110,"passed_time":0.1259918993,"remaining_time":0.4415391785},
{"learn":[508.3375493],"iteration":111,"passed_time":0.1271825365,"remaining_time":0.4405966445},
{"learn":[508.2437894],"iteration":112,"passed_time":0.1282001008,"remaining_time":0.4390569825},
{"learn":[508.1432306],"iteration":113,"passed_time":0.1292311226,"remaining_time":0.4375720469},
{"learn":[507.9720232],"iteration":114,"passed_time":0.1302994339,"remaining_time":0.4362198439},
{"learn":[507.8494233],"iteration":115,"passed_time":0.1312992076,"remaining_time":0.4346456527},
{"learn":[507.614232],"iteration":116,"passed_time":0.1324968445,"remaining_time":0.4337289866},
{"learn":[507.4948095],"iteration":117,"passed_time":0.133443163,"remaining_time":0.4319939683},
{"learn":[507.3930606],"iteration":118,"passed_time":0.1344491446,"remaining_time":0.4304632278},
{"learn":[507.2258716],"iteration":119,"passed_time":0.1354086291,"remaining_time":0.428793992},
{"learn":[507.122731],"iteration":120,"passed_time":0.1364858148,"remaining_time":0.4275051554},
{"learn":[507.016533],"iteration":121,"passed_time":0.137499671,"remaining_time":0.4260235707},
{"learn":[506.6958759],"iteration":122,"passed_time":0.1385663573,"remaining_time":0.424711518},
{"learn":[506.5496638],"iteration":123,"passed_time":0.1395338413,"remaining_time":0.4231026154},
{"learn":[506.4706996],"iteration":124,"passed_time":0.1406087771,"remaining_time":0.4218263314},
{"learn":[506.2838416],"iteration":125,"passed_time":0.1416019262,"remaining_time":0.4203104793},
{"learn":[506.1734163],"iteration":126,"passed_time":0.1427069853,"remaining_time":0.4191315394},
{"learn":[506.0569602],"iteration":127,"passed_time":0.1437132169,"remaining_time":0.4176665366},
{"learn":[505.9695905],"iteration":128,"passed_time":0.1447673207,"remaining_time":0.4163463253},
{"learn":[505.7720795],"iteration":129,"passed_time":0.1458708382,"remaining_time":0.4151708471},
{"learn":[505.5957657],"iteration":130,"passed_time":0.1470336438,"remaining_time":0.4141634699},
{"learn":[505.3806334],"iteration":131,"passed_time":0.1480321675,"remaining_time":0.4126957398},
{"learn":[505.2864453],"iteration":132,"passed_time":0.1491119781,"remaining_time":0.4114593682},
{"learn":[505.1556991],"iteration":133,"passed_time":0.1500966277,"remaining_time":0.4099654159},
{"learn":[505.0457343],"iteration":134,"passed_time":0.1511312743,"remaining_time":0.408614186},
{"learn":[504.8775615],"iteration":135,"passed_time":0.1521640043,"remaining_time":0.4072624822},
{"learn":[504.7304904],"iteration":136,"passed_time":0.1532230245,"remaining_time":0.4059850941},
{"learn":[504.611844],"iteration":137,"passed_time":0.1543327916,"remaining_time":0.4048439896},
{"learn":[504.5133426],"iteration":138,"passed_time":0.155431726,"remaining_time":0.4036752021},
{"learn":[504.3380597],"iteration":139,"passed_time":0.1565373684,"remaining_time":0.4025246616},
{"learn":[504.2550838],"iteration":140,"passed_time":0.1576039298,"remaining_time":0.4012752538},
{"learn":[504.1507541],"iteration":141,"passed_time":0.1587159051,"remaining_time":0.4001429156},
{"learn":[504.0531456],"iteration":142,"passed_time":0.1597450103,"remaining_time":0.3988039769},
{"learn":[503.9616479],"iteration":143,"passed_time":0.1607611997,"remaining_time":0.3974374104},
{"learn":[503.8837973],"iteration":144,"passed_time":0.1616981855,"remaining_time":0.3958817644},
{"learn":[503.6934176],"iteration":145,"passed_time":0.1627709548,"remaining_time":0.3946638219},
{"learn":[503.5923467],"iteration":146,"passed_time":0.1638528069,"remaining_time":0.3934696656},
{"learn":[503.5062141],"iteration":147,"passed_time":0.1649029943,"remaining_time":0.3922017161},
{"learn":[503.3905543],"iteration":148,"passed_time":0.165884894,"remaining_time":0.3907758241},
{"learn":[503.3123481],"iteration":149,"passed_time":0.166878793,"remaining_time":0.3893838504},
{"learn":[503.2168925],"iteration":150,"passed_time":0.1679295637,"remaining_time":0.3881285942},
{"learn":[502.9892958],"iteration":151,"passed_time":0.1689824175,"remaining_time":0.386880798},
{"learn":[502.889322],"iteration":152,"passed_time":0.1700043982,"remaining_time":0.3855655306},
{"learn":[502.7149851],"iteration":153,"passed_time":0.1710671265,"remaining_time":0.3843456218},
{"learn":[502.6320489],"iteration":154,"passed_time":0.1720893988,"remaining_time":0.3830376941},
{"learn":[502.5293009],"iteration":155,"passed_time":0.1731335032,"remaining_time":0.3817815711},
{"learn":[502.4512958],"iteration":156,"passed_time":0.1741049869,"remaining_time":0.3803694936},
{"learn":[502.2674344],"iteration":157,"passed_time":0.1752009215,"remaining_time":0.3792323744},
{"learn":[502.1313562],"iteration":158,"passed_time":0.1761406571,"remaining_time":0.3777607803},
{"learn":[502.0183474],"iteration":159,"passed_time":0.1772119265,"remaining_time":0.3765753438},
{"learn":[501.938637],"iteration":160,"passed_time":0.178198076,"remaining_time":0.3752120979},
{"learn":[501.7790819],"iteration":161,"passed_time":0.1793229255,"remaining_time":0.374142894},
{"learn":[501.6590175],"iteration":162,"passed_time":0.1803311154,"remaining_time":0.3728318152},
{"learn":[501.5823294],"iteration":163,"passed_time":0.1813520961,"remaining_time":0.371550636},
{"learn":[501.4377407],"iteration":164,"passed_time":0.1824002003,"remaining_time":0.3703276793},
{"learn":[501.3721237],"iteration":165,"passed_time":0.1834355968,"remaining_time":0.3690812611},
{"learn":[501.274243],"iteration":166,"passed_time":0.18522599,"remaining_time":0.3693428423},
{"learn":[501.1409993],"iteration":167,"passed_time":0.186276844,"remaining_time":0.368118525},
{"learn":[501.0393216],"iteration":168,"passed_time":0.1873205317,"remaining_time":0.3668822248},
{"learn":[500.9726936],"iteration":169,"passed_time":0.1883070145,"remaining_time":0.3655371458},
{"learn":[500.8050697],"iteration":170,"passed_time":0.1893555353,"remaining_time":0.3643156205},
{"learn":[500.6428377],"iteration":171,"passed_time":0.190410014,"remaining_time":0.3631074686},
{"learn":[500.5703607],"iteration":172,"passed_time":0.1914088294,"remaining_time":0.3617958799},
{"learn":[500.4915641],"iteration":173,"passed_time":0.1924814738,"remaining_time":0.3606262095},
{"learn":[500.3415272],"iteration":174,"passed_time":0.1936559453,"remaining_time":0.3596467556},
{"learn":[500.2149297],"iteration":175,"passed_time":0.194818751,"remaining_time":0.3586436097},
{"learn":[500.1352842],"iteration":176,"passed_time":0.1959247266,"remaining_time":0.3575349531},
{"learn":[500.083913],"iteration":177,"passed_time":0.1969923713,"remaining_time":0.3563569862},
{"learn":[499.9814353],"iteration":178,"passed_time":0.1980378922,"remaining_time":0.3551405777},
{"learn":[499.8768786],"iteration":179,"passed_time":0.1991374516,"remaining_time":0.3540221362},
{"learn":[499.8006379],"iteration":180,"passed_time":0.200991966,"remaining_time":0.3542344594},
{"learn":[499.7133475],"iteration":181,"passed_time":0.2021394392,"remaining_time":0.3531886904},
{"learn":[499.669859],"iteration":182,"passed_time":0.2031439626,"remaining_time":0.3518941865},
{"learn":[499.50176],"iteration":183,"passed_time":0.2043074765,"remaining_time":0.3508758835},
{"learn":[499.3808841],"iteration":184,"passed_time":0.2053180829,"remaining_time":0.3495956546},
{"learn":[499.2499498],"iteration":185,"passed_time":0.2063956019,"remaining_time":0.3484312849},
{"learn":[499.0251004],"iteration":186,"passed_time":0.207483912,"remaining_time":0.3472859061},
{"learn":[498.8647217],"iteration":187,"passed_time":0.2085809715,"remaining_time":0.3461556548},
{"learn":[498.7410115],"iteration":188,"passed_time":0.2095748705,"remaining_time":0.3448560039},
{"learn":[498.662074],"iteration":189,"passed_time":0.2111440269,"remaining_time":0.3444981492},
{"learn":[498.5768955],"iteration":190,"passed_time":0.2127833874,"remaining_time":0.344241187},
{"learn":[498.4983744],"iteration":191,"passed_time":0.2138895298,"remaining_time":0.343114454},
{"learn":[498.4091064],"iteration":192,"passed_time":0.2150707093,"remaining_time":0.342107294},
{"learn":[498.3098229],"iteration":193,"passed_time":0.216164394,"remaining_time":0.3409603329},
{"learn":[498.2496427],"iteration":194,"passed_time":0.2171466688,"remaining_time":0.3396396614},
{"learn":[498.1694835],"iteration":195,"passed_time":0.2181798988,"remaining_time":0.3384014756},
{"learn":[498.0910856],"iteration":196,"passed_time":0.2192918741,"remaining_time":0.3372864865},
{"learn":[497.9771792],"iteration":197,"passed_time":0.2202987723,"remaining_time":0.3360112588},
{"learn":[497.9619242],"iteration":198,"passed_time":0.2210863087,"remaining_time":0.3344069292},
{"learn":[497.8503703],"iteration":199,"passed_time":0.2222147414,"remaining_time":0.333322112},
{"learn":[497.7382678],"iteration":200,"passed_time":0.2232981767,"remaining_time":0.3321699246},
{"learn":[497.677969],"iteration":201,"passed_time":0.2243371147,"remaining_time":0.3309527732},
{"learn":[497.6080207],"iteration":202,"passed_time":0.2252945993,"remaining_time":0.3296182068},
{"learn":[497.4941292],"iteration":203,"passed_time":0.2263520778,"remaining_time":0.3284324267},
{"learn":[497.395391],"iteration":204,"passed_time":0.2273649341,"remaining_time":0.3271836856},
{"learn":[497.3329591],"iteration":205,"passed_time":0.228528323,"remaining_time":0.3261520726},
{"learn":[497.2526265],"iteration":206,"passed_time":0.2295368878,"remaining_time":0.3249000393},
{"learn":[497.1611475],"iteration":207,"passed_time":0.23061699,"remaining_time":0.3237507745},
{"learn":[497.0583293],"iteration":208,"passed_time":0.2316242216,"remaining_time":0.3225007105},
{"learn":[496.9342546],"iteration":209,"passed_time":0.2326633263,"remaining_time":0.3212969744},
{"learn":[496.8253733],"iteration":210,"passed_time":0.2336723494,"remaining_time":0.320053597},
{"learn":[496.7066828],"iteration":211,"passed_time":0.2347897411,"remaining_time":0.3189596482},
{"learn":[496.6134539],"iteration":212,"passed_time":0.2357957227,"remaining_time":0.3177153635},
{"learn":[496.5380205],"iteration":213,"passed_time":0.2371007698,"remaining_time":0.3168729915},
{"learn":[496.408736],"iteration":214,"passed_time":0.2387739617,"remaining_time":0.3165143213},
{"learn":[496.3084976],"iteration":215,"passed_time":0.2404151554,"remaining_time":0.3161014081},
{"learn":[496.2503658],"iteration":216,"passed_time":0.2414260534,"remaining_time":0.3148551757},
{"learn":[496.1255836],"iteration":217,"passed_time":0.2424731993,"remaining_time":0.3136579917},
{"learn":[496.0386069],"iteration":218,"passed_time":0.2434363085,"remaining_time":0.3123543502},
{"learn":[495.9524379],"iteration":219,"passed_time":0.2443813354,"remaining_time":0.3110307906},
{"learn":[495.7807131],"iteration":220,"passed_time":0.245388067,"remaining_time":0.3097885552},
{"learn":[495.7175478],"iteration":221,"passed_time":0.2465218327,"remaining_time":0.3087075203},
{"learn":[495.6844045],"iteration":222,"passed_time":0.24765689,"remaining_time":0.3076276167},
{"learn":[495.6274476],"iteration":223,"passed_time":0.2491907152,"remaining_time":0.3070385597},
{"learn":[495.5195393],"iteration":224,"passed_time":0.2502785252,"remaining_time":0.3058959753},
{"learn":[495.3909853],"iteration":225,"passed_time":0.2512365098,"remaining_time":0.3045964764},
{"learn":[495.2655018],"iteration":226,"passed_time":0.2522391583,"remaining_time":0.3033537013},
{"learn":[495.1904564],"iteration":227,"passed_time":0.2532210997,"remaining_time":0.3020883294},
{"learn":[495.0868651],"iteration":228,"passed_time":0.2542735785,"remaining_time":0.3009089074},
{"learn":[494.9660311],"iteration":229,"passed_time":0.2552071062,"remaining_time":0.2995909507},
{"learn":[494.8716234],"iteration":230,"passed_time":0.2562440443,"remaining_time":0.2983967442},
{"learn":[494.8231407],"iteration":231,"passed_time":0.2572395266,"remaining_time":0.2971560048},
{"learn":[494.7031064],"iteration":232,"passed_time":0.2581847202,"remaining_time":0.2958597437},
{"learn":[494.6248081],"iteration":233,"passed_time":0.259149121,"remaining_time":0.294588317},
{"learn":[494.5652752],"iteration":234,"passed_time":0.2601531027,"remaining_time":0.2933641371},
{"learn":[494.4867657],"iteration":235,"passed_time":0.2611066708,"remaining_time":0.2920854284},
{"learn":[494.4607083],"iteration":236,"passed_time":0.2618912907,"remaining_time":0.2906219808},
{"learn":[494.3533956],"iteration":237,"passed_time":0.2628570664,"remaining_time":0.2893636613},
{"learn":[494.2791045],"iteration":238,"passed_time":0.2639011708,"remaining_time":0.2881933288},
{"learn":[494.1731309],"iteration":239,"passed_time":0.2649367756,"remaining_time":0.2870148403},
{"learn":[494.0297329],"iteration":240,"passed_time":0.2660607503,"remaining_time":0.2859325075},
{"learn":[493.9225478],"iteration":241,"passed_time":0.2671833916,"remaining_time":0.2848484092},
{"learn":[493.8497641],"iteration":242,"passed_time":0.2681907482,"remaining_time":0.283642067},
{"learn":[493.750049],"iteration":243,"passed_time":0.2691803558,"remaining_time":0.2824187339},
{"learn":[493.6968568],"iteration":244,"passed_time":0.2701747548,"remaining_time":0.2812022958},
{"learn":[493.6473213],"iteration":245,"passed_time":0.2712091931,"remaining_time":0.2800290042},
{"learn":[493.56819],"iteration":246,"passed_time":0.2722552973,"remaining_time":0.2788687863},
{"learn":[493.4916271],"iteration":247,"passed_time":0.2733790219,"remaining_time":0.277788361},
{"learn":[493.4375201],"iteration":248,"passed_time":0.2748593503,"remaining_time":0.2770670559},
{"learn":[493.3249242],"iteration":249,"passed_time":0.2762193941,"remaining_time":0.2762193941},
{"learn":[493.2343521],"iteration":250,"passed_time":0.2772420414,"remaining_time":0.2750329415},
{"learn":[493.1919115],"iteration":251,"passed_time":0.2782878124,"remaining_time":0.2738705455},
{"learn":[493.1425921],"iteration":252,"passed_time":0.2793161677,"remaining_time":0.2726920689},
{"learn":[493.0630399],"iteration":253,"passed_time":0.2804213517,"remaining_time":0.2715891832},
{"learn":[492.9582878],"iteration":254,"passed_time":0.2813541711,"remaining_time":0.2703206742},
{"learn":[492.9271032],"iteration":255,"passed_time":0.2823789433,"remaining_time":0.2691424303},
{"learn":[492.7963241],"iteration":256,"passed_time":0.2833493437,"remaining_time":0.2679139709},
{"learn":[492.7539541],"iteration":257,"passed_time":0.2843829904,"remaining_time":0.2667468359},
{"learn":[492.6659857],"iteration":258,"passed_time":0.2854958406,"remaining_time":0.2656544309},
{"learn":[492.6055544],"iteration":259,"passed_time":0.2868790914,"remaining_time":0.264811469},
{"learn":[492.4741501],"iteration":260,"passed_time":0.2885384924,"remaining_time":0.2642172402},
{"learn":[492.4190234],"iteration":261,"passed_time":0.2901088154,"remaining_time":0.2635339621},
{"learn":[492.3454419],"iteration":262,"passed_time":0.2911605027,"remaining_time":0.2623765746},
{"learn":[492.2818383],"iteration":263,"passed_time":0.2921716923,"remaining_time":0.2611837856},
{"learn":[492.228358],"iteration":264,"passed_time":0.2931584251,"remaining_time":0.2599706789},
{"learn":[492.0927881],"iteration":265,"passed_time":0.2942177369,"remaining_time":0.2588231219},
{"learn":[492.0350599],"iteration":266,"passed_time":0.2952802152,"remaining_time":0.2576789893},
{"learn":[491.9324344],"iteration":267,"passed_time":0.2963412769,"remaining_time":0.2565342397},
{"learn":[491.8600286],"iteration":268,"passed_time":0.2973845063,"remaining_time":0.2553747991},
{"learn":[491.7432529],"iteration":269,"passed_time":0.2984636086,"remaining_time":0.2542467777},
{"learn":[491.6356861],"iteration":270,"passed_time":0.2994957553,"remaining_time":0.253079439},
{"learn":[491.5051431],"iteration":271,"passed_time":0.3005234857,"remaining_time":0.2519093924},
{"learn":[491.3996275],"iteration":272,"passed_time":0.3015987548,"remaining_time":0.250779917},
{"learn":[491.2988065],"iteration":273,"passed_time":0.3026116111,"remaining_time":0.249599358},
{"learn":[491.2504653],"iteration":274,"passed_time":0.3036723811,"remaining_time":0.2484592209},
{"learn":[491.1866793],"iteration":275,"passed_time":0.3046785294,"remaining_time":0.2472753282},
{"learn":[491.0628209],"iteration":276,"passed_time":0.3056873859,"remaining_time":0.2460948991},
{"learn":[490.9920556],"iteration":277,"passed_time":0.3068547746,"remaining_time":0.245042302},
{"learn":[490.8880222],"iteration":278,"passed_time":0.3086005454,"remaining_time":0.244447027},
{"learn":[490.7856657],"iteration":279,"passed_time":0.3097246867,"remaining_time":0.243355111},
{"learn":[490.7237851],"iteration":280,"passed_time":0.3107819153,"remaining_time":0.2422108165},
{"learn":[490.624038],"iteration":281,"passed_time":0.3119361797,"remaining_time":0.2411421531},
{"learn":[490.5063206],"iteration":282,"passed_time":0.3132906406,"remaining_time":0.2402263922},
{"learn":[490.3888796],"iteration":283,"passed_time":0.314411782,"remaining_time":0.2391300877},
{"learn":[490.3239823],"iteration":284,"passed_time":0.3153998064,"remaining_time":0.2379331873},
{"learn":[490.1855134],"iteration":285,"passed_time":0.3163962886,"remaining_time":0.2367440761},
{"learn":[490.1204886],"iteration":286,"passed_time":0.3174729744,"remaining_time":0.2356158311},
{"learn":[490.0071794],"iteration":287,"passed_time":0.3185572013,"remaining_time":0.2344934954},
{"learn":[489.9345394],"iteration":288,"passed_time":0.3195512254,"remaining_time":0.2333055659},
{"learn":[489.8110184],"iteration":289,"passed_time":0.3206545762,"remaining_time":0.2321981414},
{"learn":[489.6993593],"iteration":290,"passed_time":0.3216469337,"remaining_time":0.231011028},
{"learn":[489.6409804],"iteration":291,"passed_time":0.3226888298,"remaining_time":0.2298605363},
{"learn":[489.5857359],"iteration":292,"passed_time":0.3237285178,"remaining_time":0.2287092259},
{"learn":[489.4974586],"iteration":293,"passed_time":0.3246712949,"remaining_time":0.2274907712},
{"learn":[489.3690022],"iteration":294,"passed_time":0.3256692353,"remaining_time":0.2263125195},
{"learn":[489.2820674],"iteration":295,"passed_time":0.326669509,"remaining_time":0.225137094},
{"learn":[489.2381555],"iteration":296,"passed_time":0.3277450698,"remaining_time":0.224014307},
{"learn":[489.1449495],"iteration":297,"passed_time":0.3287710919,"remaining_time":0.2228582569},
{"learn":[488.9825436],"iteration":298,"passed_time":0.3298729845,"remaining_time":0.2217540799},
{"learn":[488.8996808],"iteration":299,"passed_time":0.33092538,"remaining_time":0.22061692},
{"learn":[488.7637862],"iteration":300,"passed_time":0.3319299451,"remaining_time":0.2194487013},
{"learn":[488.6895508],"iteration":301,"passed_time":0.3329631751,"remaining_time":0.2183003599},
{"learn":[488.6488233],"iteration":302,"passed_time":0.33399803,"remaining_time":0.2171538347},
{"learn":[488.5715318],"iteration":303,"passed_time":0.3349940123,"remaining_time":0.2159829816},
{"learn":[488.4524853],"iteration":304,"passed_time":0.3360680315,"remaining_time":0.2148631677},
{"learn":[488.3791548],"iteration":305,"passed_time":0.3372517526,"remaining_time":0.2138132026},
{"learn":[488.2719944],"iteration":306,"passed_time":0.338318189,"remaining_time":0.2126886334},
{"learn":[488.2038425],"iteration":307,"passed_time":0.3393426695,"remaining_time":0.2115382875},
{"learn":[488.1369007],"iteration":308,"passed_time":0.3403221111,"remaining_time":0.2103609165},
{"learn":[488.0277681],"iteration":309,"passed_time":0.3413420502,"remaining_time":0.2092096437},
{"learn":[487.943184],"iteration":310,"passed_time":0.3424073616,"remaining_time":0.2080867889},
{"learn":[487.8614978],"iteration":311,"passed_time":0.3434817559,"remaining_time":0.206969776},
{"learn":[487.7587829],"iteration":312,"passed_time":0.3445012367,"remaining_time":0.2058202277},
{"learn":[487.6722091],"iteration":313,"passed_time":0.3455210925,"remaining_time":0.20467173},
{"learn":[487.5430326],"iteration":314,"passed_time":0.3467119381,"remaining_time":0.2036244716},
{"learn":[487.4368253],"iteration":315,"passed_time":0.3478483287,"remaining_time":0.2025445964},
{"learn":[487.3336904],"iteration":316,"passed_time":0.3488188958,"remaining_time":0.201368637},
{"learn":[487.2498819],"iteration":317,"passed_time":0.3497822133,"remaining_time":0.2001898202},
{"learn":[487.1339308],"iteration":318,"passed_time":0.3508244011,"remaining_time":0.1990571053},
{"learn":[487.055651],"iteration":319,"passed_time":0.3518604226,"remaining_time":0.1979214877},
{"learn":[486.9194788],"iteration":320,"passed_time":0.352853905,"remaining_time":0.1967627695},
{"learn":[486.8397244],"iteration":321,"passed_time":0.3538945929,"remaining_time":0.1956311725},
{"learn":[486.7619218],"iteration":322,"passed_time":0.3548160379,"remaining_time":0.1944347948},
{"learn":[486.6983903],"iteration":323,"passed_time":0.3558278526,"remaining_time":0.1932892039},
{"learn":[486.6128285],"iteration":324,"passed_time":0.3568417921,"remaining_time":0.1921455803},
{"learn":[486.5405389],"iteration":325,"passed_time":0.3577960685,"remaining_time":0.1909709077},
{"learn":[486.4221459],"iteration":326,"passed_time":0.3588082997,"remaining_time":0.1898282442},
{"learn":[486.2151586],"iteration":327,"passed_time":0.3598476127,"remaining_time":0.1887005774},
{"learn":[486.140807],"iteration":328,"passed_time":0.3610143348,"remaining_time":0.1876396694},
{"learn":[486.0267502],"iteration":329,"passed_time":0.3620800628,"remaining_time":0.186526093},
{"learn":[485.934504],"iteration":330,"passed_time":0.3631470408,"remaining_time":0.1854134438},
{"learn":[485.8417483],"iteration":331,"passed_time":0.3642996387,"remaining_time":0.1843443955},
{"learn":[485.7285487],"iteration":332,"passed_time":0.3652869548,"remaining_time":0.1831919563},
{"learn":[485.6740252],"iteration":333,"passed_time":0.3664088462,"remaining_time":0.1821073906},
{"learn":[485.61241],"iteration":334,"passed_time":0.3679108816,"remaining_time":0.1812098372},
{"learn":[485.4240723],"iteration":335,"passed_time":0.3699240115,"remaining_time":0.1805581485},
{"learn":[485.3360091],"iteration":336,"passed_time":0.3709417008,"remaining_time":0.1794169057},
{"learn":[485.2264039],"iteration":337,"passed_time":0.3719371414,"remaining_time":0.1782657305},
{"learn":[485.1241214],"iteration":338,"passed_time":0.3729692465,"remaining_time":0.177132887},
{"learn":[485.0537829],"iteration":339,"passed_time":0.3739608123,"remaining_time":0.1759815587},
{"learn":[485.0076232],"iteration":340,"passed_time":0.3750187492,"remaining_time":0.1748621147},
{"learn":[484.9266306],"iteration":341,"passed_time":0.3759924827,"remaining_time":0.1737041295},
{"learn":[484.8516959],"iteration":342,"passed_time":0.3770515862,"remaining_time":0.1725862946},
{"learn":[484.7865636],"iteration":343,"passed_time":0.378116856,"remaining_time":0.1714715975},
{"learn":[484.6683016],"iteration":344,"passed_time":0.3792329977,"remaining_time":0.1703800425},
{"learn":[484.5833306],"iteration":345,"passed_time":0.3802445624,"remaining_time":0.1692417994},
{"learn":[484.4962611],"iteration":346,"passed_time":0.3812415862,"remaining_time":0.1680978752},
{"learn":[484.3892292],"iteration":347,"passed_time":0.3822520676,"remaining_time":0.1669606732},
{"learn":[484.3079968],"iteration":348,"passed_time":0.3832985052,"remaining_time":0.1658397544},
{"learn":[484.2509506],"iteration":349,"passed_time":0.3842995704,"remaining_time":0.1646998159},
{"learn":[484.1136238],"iteration":350,"passed_time":0.3853265092,"remaining_time":0.163571652},
{"learn":[483.9997708],"iteration":351,"passed_time":0.3864181107,"remaining_time":0.1624712511},
{"learn":[483.9296942],"iteration":352,"passed_time":0.3875182951,"remaining_time":0.1613744741},
{"learn":[483.861165],"iteration":353,"passed_time":0.3885323179,"remaining_time":0.1602421424},
{"learn":[483.7621058],"iteration":354,"passed_time":0.3895233004,"remaining_time":0.1591010664},
{"learn":[483.6661169],"iteration":355,"passed_time":0.3905998195,"remaining_time":0.1579954326},
{"learn":[483.5610494],"iteration":356,"passed_time":0.3916536316,"remaining_time":0.1568808665},
{"learn":[483.4566793],"iteration":357,"passed_time":0.3926099496,"remaining_time":0.1557279688},
{"learn":[483.3867807],"iteration":358,"passed_time":0.3935579347,"remaining_time":0.1545728936},
{"learn":[483.3178421],"iteration":359,"passed_time":0.394737656,"remaining_time":0.1535090884},
{"learn":[483.2685463],"iteration":360,"passed_time":0.3959412092,"remaining_time":0.1524538174},
{"learn":[483.1676115],"iteration":361,"passed_time":0.3971408876,"remaining_time":0.15139625},
{"learn":[483.1002799],"iteration":362,"passed_time":0.398257071,"remaining_time":0.1503063877},
{"learn":[483.0239115],"iteration":363,"passed_time":0.3993185493,"remaining_time":0.1491959415},
{"learn":[482.9667369],"iteration":364,"passed_time":0.4003519876,"remaining_time":0.1480753927},
{"learn":[482.9111739],"iteration":365,"passed_time":0.4014957111,"remaining_time":0.1469956975},
{"learn":[482.8472245],"iteration":366,"passed_time":0.4026592667,"remaining_time":0.1459228405},
{"learn":[482.7541811],"iteration":367,"passed_time":0.4037675339,"remaining_time":0.1448296589},
{"learn":[482.6674554],"iteration":368,"passed_time":0.4048530524,"remaining_time":0.1437283194},
{"learn":[482.566668],"iteration":369,"passed_time":0.4058729499,"remaining_time":0.1426040094},
{"learn":[482.5270426],"iteration":370,"passed_time":0.4068214766,"remaining_time":0.1414554461},
{"learn":[482.4371459],"iteration":371,"passed_time":0.4078522485,"remaining_time":0.1403362575},
{"learn":[482.3851529],"iteration":372,"passed_time":0.4089201014,"remaining_time":0.1392301686},
{"learn":[482.2871759],"iteration":373,"passed_time":0.4099297079,"remaining_time":0.1381046609},
{"learn":[482.1996148],"iteration":374,"passed_time":0.4109406059,"remaining_time":0.136980202},
{"learn":[482.1275133],"iteration":375,"passed_time":0.4120992451,"remaining_time":0.1359050702},
{"learn":[482.0322423],"iteration":376,"passed_time":0.4131276004,"remaining_time":0.134786989},
{"learn":[481.9323559],"iteration":377,"passed_time":0.4144308143,"remaining_time":0.1337580935},
{"learn":[481.8436739],"iteration":378,"passed_time":0.4154862513,"remaining_time":0.1326486449},
{"learn":[481.7861501],"iteration":379,"passed_time":0.416524856,"remaining_time":0.1315341651},
{"learn":[481.6958967],"iteration":380,"passed_time":0.4176086247,"remaining_time":0.1304341899},
{"learn":[481.618339],"iteration":381,"passed_time":0.418626314,"remaining_time":0.1293138876},
{"learn":[481.5296704],"iteration":382,"passed_time":0.4197836616,"remaining_time":0.1282367843},
{"learn":[481.4809893],"iteration":383,"passed_time":0.4208671803,"remaining_time":0.1271369607},
{"learn":[481.3941416],"iteration":384,"passed_time":0.4220071122,"remaining_time":0.1260540725},
{"learn":[481.2972223],"iteration":385,"passed_time":0.4230780483,"remaining_time":0.1249505117},
{"learn":[481.2400904],"iteration":386,"passed_time":0.42416765,"remaining_time":0.1238525696},
{"learn":[481.1921642],"iteration":387,"passed_time":0.4251295093,"remaining_time":0.1227177965},
{"learn":[481.0864753],"iteration":388,"passed_time":0.4262362349,"remaining_time":0.1216252496},
{"learn":[481.0151705],"iteration":389,"passed_time":0.4273266698,"remaining_time":0.1205280351},
{"learn":[480.9549187],"iteration":390,"passed_time":0.4283613164,"remaining_time":0.1194153031},
{"learn":[480.9090304],"iteration":391,"passed_time":0.4293953381,"remaining_time":0.1183027972},
{"learn":[480.8195396],"iteration":392,"passed_time":0.430380071,"remaining_time":0.1171772712},
{"learn":[480.7145483],"iteration":393,"passed_time":0.4314030516,"remaining_time":0.1160627499},
{"learn":[480.6467543],"iteration":394,"passed_time":0.4324324902,"remaining_time":0.1149504088},
{"learn":[480.589961],"iteration":395,"passed_time":0.4334424299,"remaining_time":0.1138333654},
{"learn":[480.5282213],"iteration":396,"passed_time":0.4343827072,"remaining_time":0.112698788},
{"learn":[480.4761535],"iteration":397,"passed_time":0.4353887721,"remaining_time":0.1115820471},
{"learn":[480.4090177],"iteration":398,"passed_time":0.436396087,"remaining_time":0.1104661774},
{"learn":[480.3629444],"iteration":399,"passed_time":0.4374927716,"remaining_time":0.1093731929},
{"learn":[480.2889889],"iteration":400,"passed_time":0.4385438756,"remaining_time":0.1082689369},
{"learn":[480.225685],"iteration":401,"passed_time":0.4395116928,"remaining_time":0.1071446415},
{"learn":[480.1610135],"iteration":402,"passed_time":0.4409593981,"remaining_time":0.1061366293},
{"learn":[480.1140418],"iteration":403,"passed_time":0.4423337744,"remaining_time":0.1051090157},
{"learn":[480.0191001],"iteration":404,"passed_time":0.4434298757,"remaining_time":0.1040144153},
{"learn":[479.9712026],"iteration":405,"passed_time":0.4444159835,"remaining_time":0.102894341},
{"learn":[479.8648633],"iteration":406,"passed_time":0.4455450828,"remaining_time":0.1018075988},
{"learn":[479.8164977],"iteration":407,"passed_time":0.4466202687,"remaining_time":0.100708492},
{"learn":[479.7221434],"iteration":408,"passed_time":0.4475649206,"remaining_time":0.09958045912},
{"learn":[479.633335],"iteration":409,"passed_time":0.4486457312,"remaining_time":0.09848320928},
{"learn":[479.5553085],"iteration":410,"passed_time":0.4497693308,"remaining_time":0.09739530521},
{"learn":[479.4662996],"iteration":411,"passed_time":0.4507934364,"remaining_time":0.0962859767},
{"learn":[479.3700797],"iteration":412,"passed_time":0.4518247915,"remaining_time":0.09517858804},
{"learn":[479.2983113],"iteration":413,"passed_time":0.4529730563,"remaining_time":0.09409585228},
{"learn":[479.2357356],"iteration":414,"passed_time":0.4539689552,"remaining_time":0.09298159324},
{"learn":[479.1771177],"iteration":415,"passed_time":0.4549866862,"remaining_time":0.09187231163},
{"learn":[479.1046116],"iteration":416,"passed_time":0.4559722107,"remaining_time":0.09075705872},
{"learn":[479.0389974],"iteration":417,"passed_time":0.4569131545,"remaining_time":0.08963368104},
{"learn":[478.9585214],"iteration":418,"passed_time":0.4579198028,"remaining_time":0.08852387596},
{"learn":[478.9092447],"iteration":419,"passed_time":0.458861455,"remaining_time":0.0874021819},
{"learn":[478.8433821],"iteration":420,"passed_time":0.4602387061,"remaining_time":0.08636308262},
{"learn":[478.7394281],"iteration":421,"passed_time":0.4612886435,"remaining_time":0.08526188197},
{"learn":[478.6806384],"iteration":422,"passed_time":0.4622732514,"remaining_time":0.08414903158},
{"learn":[478.6264748],"iteration":423,"passed_time":0.463279483,"remaining_time":0.08304066205},
{"learn":[478.5475138],"iteration":424,"passed_time":0.4642346344,"remaining_time":0.08192375901},
{"learn":[478.5137348],"iteration":425,"passed_time":0.4651755782,"remaining_time":0.08080514739},
{"learn":[478.4531524],"iteration":426,"passed_time":0.4662117247,"remaining_time":0.07970364381},
{"learn":[478.3607038],"iteration":427,"passed_time":0.4671755006,"remaining_time":0.07859027112},
{"learn":[478.3132124],"iteration":428,"passed_time":0.468195898,"remaining_time":0.0774869668},
{"learn":[478.251576],"iteration":429,"passed_time":0.4693003321,"remaining_time":0.07639772848},
{"learn":[478.1801279],"iteration":430,"passed_time":0.4703662685,"remaining_time":0.07530225645},
{"learn":[478.0971406],"iteration":431,"passed_time":0.471503159,"remaining_time":0.07421808985},
{"learn":[478.0365616],"iteration":432,"passed_time":0.4724901418,"remaining_time":0.07311048383},
{"learn":[477.9720944],"iteration":433,"passed_time":0.4739474715,"remaining_time":0.07207496111},
{"learn":[477.8461156],"iteration":434,"passed_time":0.4754573814,"remaining_time":0.07104535584},
{"learn":[477.7940039],"iteration":435,"passed_time":0.4768074675,"remaining_time":0.06999008698},
{"learn":[477.7323747],"iteration":436,"passed_time":0.4781427629,"remaining_time":0.06893133652},
{"learn":[477.6680405],"iteration":437,"passed_time":0.4796719633,"remaining_time":0.06789877106},
{"learn":[477.5933898],"iteration":438,"passed_time":0.482268475,"remaining_time":0.06701224824},
{"learn":[477.5198654],"iteration":439,"passed_time":0.4835773969,"remaining_time":0.06594237231},
{"learn":[477.4383104],"iteration":440,"passed_time":0.4849185669,"remaining_time":0.06487572664},
{"learn":[477.3869802],"iteration":441,"passed_time":0.4860616237,"remaining_time":0.06378184203},
{"learn":[477.2968206],"iteration":442,"passed_time":0.4871117694,"remaining_time":0.06267578071},
{"learn":[477.2139083],"iteration":443,"passed_time":0.4881434578,"remaining_time":0.06156764333},
{"learn":[477.1392528],"iteration":444,"passed_time":0.4892140606,"remaining_time":0.06046465918},
{"learn":[477.0632444],"iteration":445,"passed_time":0.4903039956,"remaining_time":0.0593641609},
{"learn":[476.9849696],"iteration":446,"passed_time":0.4912936865,"remaining_time":0.05825182413},
{"learn":[476.8864786],"iteration":447,"passed_time":0.4923959958,"remaining_time":0.05715310665},
{"learn":[476.823028],"iteration":448,"passed_time":0.4933408144,"remaining_time":0.05603648449},
{"learn":[476.786515],"iteration":449,"passed_time":0.4944106672,"remaining_time":0.05493451858},
{"learn":[476.7186685],"iteration":450,"passed_time":0.4955036437,"remaining_time":0.05383520741},
{"learn":[476.6544315],"iteration":451,"passed_time":0.4965084587,"remaining_time":0.05272656199},
{"learn":[476.619571],"iteration":452,"passed_time":0.4974815673,"remaining_time":0.05161508535},
{"learn":[476.5573995],"iteration":453,"passed_time":0.4985031314,"remaining_time":0.05050912785},
{"learn":[476.480001],"iteration":454,"passed_time":0.4994715319,"remaining_time":0.04939828338},
{"learn":[476.4400302],"iteration":455,"passed_time":0.5003972684,"remaining_time":0.04828394695},
{"learn":[476.3557371],"iteration":456,"passed_time":0.5013859594,"remaining_time":0.04717635942},
{"learn":[476.2927003],"iteration":457,"passed_time":0.5023350694,"remaining_time":0.04606566139},
{"learn":[476.2024387],"iteration":458,"passed_time":0.5037040711,"remaining_time":0.0449931741},
{"learn":[476.1210998],"iteration":459,"passed_time":0.5052396461,"remaining_time":0.04393388227},
{"learn":[476.0588188],"iteration":460,"passed_time":0.507503511,"remaining_time":0.04293413651},
{"learn":[476.0013646],"iteration":461,"passed_time":0.5086664,"remaining_time":0.0418383619},
{"learn":[475.9649232],"iteration":462,"passed_time":0.5096873391,"remaining_time":0.04073095366},
{"learn":[475.9063048],"iteration":463,"passed_time":0.510666364,"remaining_time":0.03962066617},
{"learn":[475.8582539],"iteration":464,"passed_time":0.5116731789,"remaining_time":0.03851303497},
{"learn":[475.7560738],"iteration":465,"passed_time":0.5126856602,"remaining_time":0.03740624988},
{"learn":[475.700232],"iteration":466,"passed_time":0.5136762261,"remaining_time":0.03629832004},
{"learn":[475.6251771],"iteration":467,"passed_time":0.5147039564,"remaining_time":0.03519343292},
{"learn":[475.5584425],"iteration":468,"passed_time":0.5157596434,"remaining_time":0.0340907227},
{"learn":[475.4985984],"iteration":469,"passed_time":0.5168208301,"remaining_time":0.03298856362},
{"learn":[475.4256865],"iteration":470,"passed_time":0.5177671903,"remaining_time":0.03187950853},
{"learn":[475.3592226],"iteration":471,"passed_time":0.5187908792,"remaining_time":0.03077573012},
{"learn":[475.2889942],"iteration":472,"passed_time":0.5199147705,"remaining_time":0.02967801016},
{"learn":[475.2124791],"iteration":473,"passed_time":0.520906253,"remaining_time":0.02857291683},
{"learn":[475.1563811],"iteration":474,"passed_time":0.5219612734,"remaining_time":0.02747164597},
{"learn":[475.0654636],"iteration":475,"passed_time":0.5232540713,"remaining_time":0.02638255821},
{"learn":[475.0144376],"iteration":476,"passed_time":0.5244260013,"remaining_time":0.02528678832},
{"learn":[474.9028711],"iteration":477,"passed_time":0.5256617609,"remaining_time":0.02419363753},
{"learn":[474.8317443],"iteration":478,"passed_time":0.526812109,"remaining_time":0.02309614674},
{"learn":[474.7751874],"iteration":479,"passed_time":0.5279658318,"remaining_time":0.02199857632},
{"learn":[474.7313795],"iteration":480,"passed_time":0.5288806105,"remaining_time":0.02089133389},
{"learn":[474.6434634],"iteration":481,"passed_time":0.5299177987,"remaining_time":0.01978946136},
{"learn":[474.5671694],"iteration":482,"passed_time":0.5309907346,"remaining_time":0.01868911488},
{"learn":[474.5062701],"iteration":483,"passed_time":0.5320077573,"remaining_time":0.0175870333},
{"learn":[474.4484405],"iteration":484,"passed_time":0.5330091142,"remaining_time":0.01648481797},
{"learn":[474.415681],"iteration":485,"passed_time":0.5339633489,"remaining_time":0.01538166026},
{"learn":[474.353785],"iteration":486,"passed_time":0.5352766456,"remaining_time":0.01428869896},
{"learn":[474.3156951],"iteration":487,"passed_time":0.5364047449,"remaining_time":0.01319028061},
{"learn":[474.2695616],"iteration":488,"passed_time":0.5376203807,"remaining_time":0.01209371},
{"learn":[474.2046084],"iteration":489,"passed_time":0.5390051731,"remaining_time":0.01100010557},
{"learn":[474.1303694],"iteration":490,"passed_time":0.5400914416,"remaining_time":0.009899843126},
{"learn":[474.0863208],"iteration":491,"passed_time":0.5411212135,"remaining_time":0.008798718919},
{"learn":[474.0340281],"iteration":492,"passed_time":0.5422095653,"remaining_time":0.007698715937},
{"learn":[473.982766],"iteration":493,"passed_time":0.5433582467,"remaining_time":0.006599492875},
{"learn":[473.9114197],"iteration":494,"passed_time":0.544425558,"remaining_time":0.005499248061},
{"learn":[473.8673255],"iteration":495,"passed_time":0.5454529551,"remaining_time":0.004398814154},
{"learn":[473.7839177],"iteration":496,"passed_time":0.54646052,"remaining_time":0.003298554446},
{"learn":[473.735123],"iteration":497,"passed_time":0.5474798341,"remaining_time":0.002198714193},
{"learn":[473.688583],"iteration":498,"passed_time":0.5484812744,"remaining_time":0.001099160871},
{"learn":[473.6369651],"iteration":499,"passed_time":0.5494945473,"remaining_time":0}
]}